{
  "schemaVersion": "1.0.0",
  "runId": "2026-05-18T20-59-43-bb8f4dc5",
  "correlationId": "corr-2026-05-18T20-59-43-bb8f4dc5",
  "providerMode": "bootstrap",
  "productId": "phr",
  "providerRefs": {
    "eventProviderId": "file-lifecycle-events",
    "artifactProviderId": "file-artifact-manifests",
    "healthProviderId": "file-health-snapshots",
    "approvalProviderId": "file-approvals",
    "provenanceProviderId": "file-provenance",
    "runtimeTruthProviderId": "file-runtime-truth"
  },
  "phase": "deploy",
  "phaseMode": "sequential",
  "lifecycleProfile": "standard-web-api-product",
  "environment": "local",
  "surfaces": [
    {
      "surface": "local",
      "type": "backend-api",
      "adapter": "compose-local",
      "config": {
        "adapter": "compose-local",
        "target": "compose-local",
        "composeFile": "products/phr/deploy/local.compose.yaml",
        "envFile": "products/phr/deploy/local.env",
        "envExampleFile": "products/phr/deploy/local.env.example",
        "requireEnvFile": false,
        "expectedServices": [
          "phr-api",
          "phr-web"
        ],
        "healthChecks": {
          "backend-api": {
            "type": "http",
            "url": "http://localhost:${PHR_API_PORT:-8085}/health/ready",
            "retries": 10,
            "intervalMs": 3000
          },
          "web": {
            "type": "http",
            "url": "http://localhost:${PHR_WEB_PORT:-5178}/",
            "retries": 5,
            "intervalMs": 2000
          }
        }
      }
    }
  ],
  "gates": [
    {
      "gateId": "artifact-validation",
      "gateName": "artifact-validation",
      "required": true,
      "phase": "deploy",
      "source": "lifecycle-profile",
      "status": "pending"
    },
    {
      "gateId": "environment-validation",
      "gateName": "environment-validation",
      "required": true,
      "phase": "deploy",
      "source": "lifecycle-profile",
      "status": "pending"
    },
    {
      "gateId": "health-check",
      "gateName": "health-check",
      "required": true,
      "phase": "deploy",
      "source": "lifecycle-profile",
      "status": "pending"
    },
    {
      "gateId": "observability-check",
      "gateName": "observability-check",
      "required": true,
      "phase": "deploy",
      "source": "lifecycle-profile",
      "status": "pending"
    },
    {
      "gateId": "consent",
      "gateName": "consent",
      "required": true,
      "phase": "deploy",
      "source": "lifecycle-profile",
      "status": "pending"
    },
    {
      "gateId": "tenant-data-sovereignty",
      "gateName": "tenant-data-sovereignty",
      "required": true,
      "phase": "deploy",
      "source": "lifecycle-profile",
      "status": "pending"
    }
  ],
  "steps": [
    {
      "id": "deploy-local-0",
      "stepKind": "deploy",
      "phase": "deploy",
      "surface": "local",
      "adapter": "compose-local",
      "adapterSelectionSource": "product-config-override",
      "description": "deploy to local via compose-local",
      "dependsOn": [],
      "estimatedDurationMs": 90000,
      "adapterContext": {
        "deploymentConfig": {
          "adapter": "compose-local",
          "target": "compose-local",
          "composeFile": "products/phr/deploy/local.compose.yaml",
          "envFile": "products/phr/deploy/local.env",
          "envExampleFile": "products/phr/deploy/local.env.example",
          "requireEnvFile": false,
          "expectedServices": [
            "phr-api",
            "phr-web"
          ],
          "healthChecks": {
            "backend-api": {
              "type": "http",
              "url": "http://localhost:${PHR_API_PORT:-8085}/health/ready",
              "retries": 10,
              "intervalMs": 3000
            },
            "web": {
              "type": "http",
              "url": "http://localhost:${PHR_WEB_PORT:-5178}/",
              "retries": 5,
              "intervalMs": 2000
            }
          }
        },
        "environmentConfig": {
          "environment": "local"
        },
        "surfaceConfig": {
          "adapter": "compose-local",
          "expectedReportFields": [
            "schemaVersion",
            "productUnitId",
            "runId",
            "correlationId",
            "environment",
            "status",
            "checkedAt",
            "checks",
            "evidenceRefs"
          ],
          "healthChecks": {
            "backend-api": {
              "type": "http",
              "url": "http://localhost:${PHR_API_PORT:-8085}/health/ready",
              "retries": 10,
              "intervalMs": 3000
            },
            "web": {
              "type": "http",
              "url": "http://localhost:${PHR_WEB_PORT:-5178}/",
              "retries": 5,
              "intervalMs": 2000
            }
          }
        }
      }
    }
  ],
  "expectedArtifacts": [],
  "requiredManifests": [
    "deployment-manifest",
    "lifecycle-health-snapshot"
  ],
  "requiredPlugins": [],
  "approvalRequirements": [],
  "outputDirectory": "/Users/samujjwal/Development/ghatana/.kernel-runs/phr/deploy",
  "estimatedDurationMs": 90000
}
