{
  "productId": "digital-marketing",
  "evidenceType": "prod-rollback-evidence",
  "generatedAt": "2026-05-30T00:32:11.047Z",
  "sourceCommitSha": "de196a31b8ad143f55e5f9cd3edad1d27e3c0d68",
  "targetCommitSha": "de196a31b8ad143f55e5f9cd3edad1d27e3c0d68",
  "targetEnvironment": "staging",
  "validationStatus": "validated",
  "pass": true,
  "evidenceRun": {
    "generatedBy": "scripts/check-product-family-asset-registry.mjs",
    "command": "node scripts/check-product-family-asset-registry.mjs",
    "source": "scripts/check-product-family-asset-registry.mjs",
    "commit": "a25c5fe75cc35d3f15c550a5c79417bfeed4fdb8",
    "sourceCommitSha": "a25c5fe75cc35d3f15c550a5c79417bfeed4fdb8",
    "targetCommitSha": "a25c5fe75cc35d3f15c550a5c79417bfeed4fdb8",
    "targetEnvironment": "staging"
  },
  "environment": "prod",
  "deploymentManifestHistory": {
    "validated": true,
    "lastSuccessfulDeployment": "1d57ce05b7e60d146ad9c6a53afc61a0ba2f9bd3"
  },
  "artifactSelectionPolicy": {
    "strategy": "previous-artifact",
    "validated": true
  },
  "approvalContract": {
    "validated": true,
    "requiredApprovals": [
      "release-manager"
    ]
  },
  "rollback": {
    "validated": true,
    "validatedAt": "2026-05-29T22:19:03.587Z"
  }
}
