{
  "common_imports": {
    "List": ["java.util.List"],
    "ArrayList": ["java.util.ArrayList"],
    "Map": ["java.util.Map"],
    "HashMap": ["java.util.HashMap"],
    "Set": ["java.util.Set"],
    "HashSet": ["java.util.HashSet"],
    "Arrays": ["java.util.Arrays"],
    "Collections": ["java.util.Collections"],
    "Optional": ["java.util.Optional"],
    "Date": ["java.util.Date", "java.sql.Date"],
    "LocalDate": ["java.time.LocalDate"],
    "LocalDateTime": ["java.time.LocalDateTime"],
    "Instant": ["java.time.Instant"],
    "Duration": ["java.time.Duration"],
    "Path": ["java.nio.file.Path"],
    "Paths": ["java.nio.file.Paths"],
    "Files": ["java.nio.file.Files"],
    "IOException": ["java.io.IOException"],
    "InputStream": ["java.io.InputStream"],
    "OutputStream": ["java.io.OutputStream"],
    "BufferedReader": ["java.io.BufferedReader"],
    "BufferedWriter": ["java.io.BufferedWriter"],
    "StringUtils": ["org.apache.commons.lang3.StringUtils"],
    "CollectionUtils": ["org.apache.commons.collections4.CollectionUtils"],
    "Objects": ["java.util.Objects"],
    "UUID": ["java.util.UUID"],
    "BigDecimal": ["java.math.BigDecimal"],
    "BigInteger": ["java.math.BigInteger"],
    "Pattern": ["java.util.regex.Pattern"],
    "Matcher": ["java.util.regex.Matcher"],
    "AtomicInteger": ["java.util.concurrent.atomic.AtomicInteger"],
    "AtomicLong": ["java.util.concurrent.atomic.AtomicLong"],
    "CompletableFuture": ["java.util.concurrent.CompletableFuture"],
    "ExecutorService": ["java.util.concurrent.ExecutorService"],
    "Executors": ["java.util.concurrent.Executors"],
    "CountDownLatch": ["java.util.concurrent.CountDownLatch"],
    "ConcurrentHashMap": ["java.util.concurrent.ConcurrentHashMap"],
    "LinkedList": ["java.util.LinkedList"],
    "TreeMap": ["java.util.TreeMap"],
    "TreeSet": ["java.util.TreeSet"],
    "LinkedHashMap": ["java.util.LinkedHashMap"],
    "LinkedHashSet": ["java.util.LinkedHashSet"],
    "Queue": ["java.util.Queue"],
    "Deque": ["java.util.Deque"],
    "Stack": ["java.util.Stack"]
  },
  "static_imports": {
    "PI": "java.lang.Math",
    "E": "java.lang.Math",
    "sort": "java.util.Arrays",
    "asList": "java.util.Arrays",
    "emptyList": "java.util.Collections",
    "singletonList": "java.util.Collections",
    "unmodifiableList": "java.util.Collections"
  }
}

