{
  "schemaVersion": "1.0.0",
  "productId": "yappc",
  "evidenceType": "release-cockpit-datacloud-persistence",
  "generatedAt": "2026-05-24T00:00:00.000Z",
  "validationStatus": "passed",
  "requirement": "Release cockpit records must be persisted through Data Cloud for durability",
  "persistenceStatus": {
    "overall": "persisted",
    "mechanism": "YappcDataCloudRepository with Data Cloud backend"
  },
  "dataCloudAdapter": {
    "implementation": "YappcDataCloudRepository",
    "file": "products/yappc/infrastructure/datacloud/src/main/java/com/ghatana/yappc/infrastructure/datacloud/adapter/YappcDataCloudRepository.java",
    "features": {
      "crudOperations": true,
      "tenantIsolation": true,
      "caching": true,
      "retryPolicy": true,
      "circuitBreaker": true
    },
    "tenantResolution": {
      "method": "TenantContext.getCurrentTenantId()",
      "security": "Throws SecurityException if no tenant context or default-tenant",
      "preventsCrossTenantAccess": true
    }
  },
  "persistenceCapabilities": {
    "save": {
      "method": "save(T domainEntity)",
      "tenantScoped": true,
      "cacheInvalidation": true,
      "retryEnabled": true,
      "circuitBreakerEnabled": true
    },
    "findById": {
      "method": "findById(UUID id)",
      "tenantScoped": true,
      "caching": true,
      "redisCache": true,
      "inMemoryCache": true
    },
    "deleteById": {
      "method": "deleteById(UUID id)",
      "tenantScoped": true,
      "cacheInvalidation": true
    },
    "query": {
      "method": "findByFilter / findByField / findByFilterPaginated",
      "tenantScoped": true,
      "pagination": true
    }
  },
  "resilience": {
    "retryPolicy": {
      "maxRetries": 3,
      "initialDelay": "100ms",
      "maxDelay": "10s",
      "multiplier": 2.0,
      "jitter": 0.1,
      "maxDuration": "30s"
    },
    "circuitBreaker": {
      "failureThreshold": 5,
      "successThreshold": 2,
      "resetTimeout": "30s",
      "maxBackoff": "5m",
      "backoffMultiplier": 2.0
    }
  },
  "caching": {
    "redisCache": {
      "optional": true,
      "adapter": "RedisEntityCacheAdapter",
      "invalidationOnWrite": true
    },
    "inMemoryCache": {
      "defaultSize": 1000,
      "defaultTtl": "5m",
      "invalidationOnWrite": true
    }
  },
  "releaseCockpitCollections": {
    "releaseBlockers": {
      "collection": "yappc-release-blockers",
      "persistence": "via YappcDataCloudRepository",
      "tenantScoped": true
    },
    "evidenceFreshness": {
      "collection": "yappc-evidence-freshness",
      "persistence": "via YappcDataCloudRepository",
      "tenantScoped": true
    },
    "assetPromotion": {
      "collection": "yappc-asset-promotion",
      "persistence": "via YappcDataCloudRepository",
      "tenantScoped": true
    }
  },
  "evidenceRefs": [
    "products/yappc/infrastructure/datacloud/src/main/java/com/ghatana/yappc/infrastructure/datacloud/adapter/YappcDataCloudRepository.java",
    ".kernel/evidence/yappc/release-blockers-cockpit.json",
    ".kernel/evidence/yappc/evidence-freshness-validation.json"
  ],
  "summary": {
    "totalCapabilities": 5,
    "capabilitiesImplemented": 5,
    "overallStatus": "passed",
    "dataCloudPersistence": true,
    "tenantIsolation": true,
    "resilienceEnabled": true,
    "cachingEnabled": true
  }
}
